Metadata-Version: 2.1
Name: PyVoltammetry
Version: 1.0
Summary: A Python package for analysing CV curves of electrocatalysts
Home-page: https://github.com/kkyang26/PyVoltammetry
Author: Yang Li
Author-email: yli52156@gmail.com
License: UNKNOWN
Platform: UNKNOWN
Classifier: Programming Language :: Python :: 3
Classifier: License :: OSI Approved :: MIT License
Classifier: Operating System :: OS Independent
License-File: LICENSE
